chemlibmgr/__init__.py
chemlibmgr/analyse.py
chemlibmgr/config.py
chemlibmgr/db.py
chemlibmgr/io.py
chemlibmgr/manager.py
chemlibmgr-0.0.1.dist-info/LICENSE
chemlibmgr-0.0.1.dist-info/METADATA
chemlibmgr-0.0.1.dist-info/WHEEL
chemlibmgr-0.0.1.dist-info/top_level.txt
chemlibmgr-0.0.1.dist-info/RECORD
