Metadata-Version: 2.1
Name: chemlibmgr
Version: 0.0.1
Summary: Fundamental package for compound library management
Author: Jake J. Tian et al.
Project-URL: Homepage, https://github.com/ojtian/chemlibmgr
Classifier: Programming Language :: Python :: 3
Classifier: License :: OSI Approved :: Apache Software License
Classifier: Operating System :: OS Independent
Requires-Python: >=3.10
License-File: LICENSE
